[
  {
    "kb_id": "e97dea78f49a16f6fc4bf53645fc95c03d453f5a",
    "kb_title": "a",
    "kb_body": "aaaa",
    "kb_permalink": "",
    "kb_keywords": "a",
    "kb_liked_count": 2,
    "kb_published": false,
    "kb_suggestion": false,
    "kb_featured": false,
    "kb_author_email": "a",
    "kb_published_date": "a"
  },
  {
    "kb_id": "5c2b64733bade538451095c3a0a148284051437c",
    "kb_title": "a",
    "kb_body": "aaaaasdfkfjkjfbkfjbvlkjfvbsldfkvbdklfv dfkjlvbkjfbkjfbkfjbvdfkjvblakdjfçidofnajfkbfhvbadkjdljweiorhruifbjfvfkvnsçadlkfjçjfgasdfasdf",
    "kb_permalink": "",
    "kb_keywords": "a",
    "kb_liked_count": 3,
    "kb_published": false,
    "kb_suggestion": false,
    "kb_featured": false,
    "kb_author_email": "a",
    "kb_published_date": "a"
  }
]